{"doc":{"name":"random","description":"Get a random number.","examples":{},"_return":{"description":"The random value","var":"number"},"calls":[{"arguments":[{"name":"max","description":"The maximum of the range"}],"example":{"live":false,"source":"random()      -- random number between 0 and 1\nrandom(3)     -- random number between 0 and 3"}},{"arguments":[{"name":"min","description":"The minimum of the range"},{"name":"max","description":"The maximum of the range"}],"example":{"live":false,"source":"random(3, 12) -- random number between 3 and 12"}},{"arguments":[{"name":"arr","description":"The array to randomly select an item from"}],"example":{"live":false,"source":"random({ 'A', 'B', 'C' }) -- random element in table"}}],"_type":"method","bottom_description":""},"source":{"end_line":45,"header":"lu5_math.h","start_line":18}}