{"doc":{"_return":{"var":"Vector","description":"The created vector"},"name":"createVector","examples":{},"_type":"method","visual":false,"description":"Create a vector instance.","calls":[{"example":"local point = createVector(80, 125);\n\nprint(point);","arguments":[{"description":"The first component of the vector","name":"x"},{"description":"The second component of the vector","name":"y"}]},{"example":"local point = createVector(130, 200, 60);\n\nprint(point);","arguments":[{"description":"The first component of the vector","name":"x"},{"description":"The second component of the vector","name":"y"},{"description":"The third component of the vector","name":"z"}]}],"bottom_description":""},"source":{"start_line":18,"end_line":44,"header":"lu5_vector.h"}}