{"doc":{"calls":[{"arguments":[{"description":"The pressed key as a string, is nil if glfw cannot find a name for the key","name":"key"},{"description":"The pressed key as a key code","name":"keyCode"}]}],"description":"Called whenever a key is pressed.","_type":"event","examples":[{"live":false,"source":"function setup()\n   createWindow(600, 600);\nend\n\nfunction draw()\n   background(51);\nend\n\nfunction keyPressed(key, keyCode)\n   print(key, keyCode)\nend"}],"bottom_description":"","name":"keyPressed"},"source":{"header":"keyboard.h","start_line":27,"end_line":49}}