{"methods":[{"source":{"header":"io.h","start_line":6,"end_line":21},"doc":{"name":"print","examples":["print(42);\n\nprint(1, 2, 3);\n\nprint('Hello world');\n\nprint({ 3, 8, 1 });"],"_type":"method","description":"Printing utility, can take any lua type.","bottom_description":"","calls":[{"arguments":[{"description":"The value to print to stdout","name":"value"}]}]}},{"source":{"header":"io.h","start_line":25,"end_line":35},"doc":{"name":"loadText","examples":["file = loadText(\"./your-file.txt\");\nprint(file)"],"_type":"method","description":"Read a file as a string","bottom_description":"","calls":[{"arguments":[{"description":"The path of the file","name":"file_path"}]}]}},{"source":{"header":"io.h","start_line":37,"end_line":47},"doc":{"name":"loadStrings","examples":["file = loadStrings(\"./your-file.txt\");\nprint(file)"],"_type":"method","description":"Read a file as an array of strings split by line","bottom_description":"","calls":[{"arguments":[{"description":"The path of the file","name":"file_path"}]}]}}],"name":"io","source":"io"}