{"doc":{"description":"Create a GLFW window.","bottom_description":"It is also possible to create a window in the global scope without defining a setup function.","examples":["function setup()\n  -- Create the window here\n  createWindow(600, 600);\nend\n\nfunction draw()\n  -- draw things\nend"],"name":"createWindow","calls":[{"arguments":[{"name":"w","description":"Window width"},{"name":"h","description":"Window height"},{"name":"[mode]","description":"Rendering mode, either `GL2D` or `GL3D`, by default `GL2D` is set."}]}],"_type":"method"},"source":{"header":"window.h","start_line":7,"end_line":28}}